stackit/iaas/__init__.py
stackit/iaas/api/__init__.py
stackit/iaas/api/default_api.py
stackit/iaas/api_client.py
stackit/iaas/api_response.py
stackit/iaas/configuration.py
stackit/iaas/exceptions.py
stackit/iaas/models/__init__.py
stackit/iaas/models/add_routes_to_routing_table_payload.py
stackit/iaas/models/add_routing_table_to_area_payload.py
stackit/iaas/models/add_volume_to_server_payload.py
stackit/iaas/models/affinity_group.py
stackit/iaas/models/affinity_group_list_response.py
stackit/iaas/models/allowed_addresses_inner.py
stackit/iaas/models/area_id.py
stackit/iaas/models/availability_zone_list_response.py
stackit/iaas/models/backup.py
stackit/iaas/models/backup_list_response.py
stackit/iaas/models/backup_source.py
stackit/iaas/models/base_security_group_rule.py
stackit/iaas/models/boot_volume.py
stackit/iaas/models/boot_volume_source.py
stackit/iaas/models/create_affinity_group_payload.py
stackit/iaas/models/create_backup_payload.py
stackit/iaas/models/create_image_payload.py
stackit/iaas/models/create_isolated_network_payload.py
stackit/iaas/models/create_key_pair_payload.py
stackit/iaas/models/create_network_area_payload.py
stackit/iaas/models/create_network_area_range_payload.py
stackit/iaas/models/create_network_area_region_payload.py
stackit/iaas/models/create_network_area_route_payload.py
stackit/iaas/models/create_network_ipv4.py
stackit/iaas/models/create_network_ipv4_with_prefix.py
stackit/iaas/models/create_network_ipv4_with_prefix_length.py
stackit/iaas/models/create_network_ipv6.py
stackit/iaas/models/create_network_ipv6_with_prefix.py
stackit/iaas/models/create_network_ipv6_with_prefix_length.py
stackit/iaas/models/create_network_payload.py
stackit/iaas/models/create_nic_payload.py
stackit/iaas/models/create_protocol.py
stackit/iaas/models/create_public_ip_payload.py
stackit/iaas/models/create_security_group_payload.py
stackit/iaas/models/create_security_group_rule_payload.py
stackit/iaas/models/create_security_group_rule_protocol.py
stackit_iaas-1.1.0.dist-info/METADATA
stackit_iaas-1.1.0.dist-info/WHEEL
stackit_iaas-1.1.0.dist-info/licenses/LICENSE.md
stackit_iaas-1.1.0.dist-info/licenses/NOTICE.txt
stackit_iaas-1.1.0.dist-info/RECORD
